{
  "type": "eidolon:worktable",
  "core": [
    " D ",
    " A ",
    " G "
  ],
  "extras": [
    "Z",
    "SS",
    "W"
  ],
  "key": {
    "D": {
      "tag": "forge:storage_blocks/diamond"
    },
    "G": {
      "tag": "forge:glass"
    },
    "A": {
      "item": "eidolon:basic_amulet"
    },
    "Z": {
      "item": "eidolon:zombie_heart"
    },
    "W": {
      "item": "eidolon:wraith_heart"
    },
    "S": {
      "item": "eidolon:lesser_soul_gem"
    }
  },
  "result": {
    "item": "eidolon:glass_hand"
  }
}